{
  "generated_at": "2026-04-17T05:57:03Z",
  "backend": "internal-event-log",
  "published_events": 8,
  "last_event_at": "2026-04-17T05:57:03Z",
  "entries": [
    {
      "id": "evt-0001",
      "at": "2026-04-17T05:56:59Z",
      "type": "workflow.started",
      "source": "profile-readme-automation",
      "details": "Trigger=schedule"
    },
    {
      "id": "evt-0002",
      "at": "2026-04-17T05:56:59Z",
      "type": "task.dispatched",
      "source": "wakatime",
      "details": "Dispatched on pool metrics-pool attempt 1/2"
    },
    {
      "id": "evt-0003",
      "at": "2026-04-17T05:56:59Z",
      "type": "task.dispatched",
      "source": "daily-quote",
      "details": "Dispatched on pool engagement-pool attempt 1/2"
    },
    {
      "id": "evt-0004",
      "at": "2026-04-17T05:57:01Z",
      "type": "task.succeeded",
      "source": "wakatime",
      "details": "Updated WakaTime section"
    },
    {
      "id": "evt-0005",
      "at": "2026-04-17T05:57:01Z",
      "type": "task.succeeded",
      "source": "daily-quote",
      "details": "Updated daily quote: Abraham Lincoln"
    },
    {
      "id": "evt-0006",
      "at": "2026-04-17T05:57:01Z",
      "type": "task.dispatched",
      "source": "snapshot",
      "details": "Dispatched on pool content-pool attempt 1/2"
    },
    {
      "id": "evt-0007",
      "at": "2026-04-17T05:57:03Z",
      "type": "task.succeeded",
      "source": "snapshot",
      "details": "Updated recent repository snapshot with 5 entries and refreshed showcase assets"
    },
    {
      "id": "evt-0008",
      "at": "2026-04-17T05:57:03Z",
      "type": "workflow.completed",
      "source": "profile-readme-automation",
      "details": "All terminal task states reached"
    }
  ]
}
